openapi_conformance/__init__.py
openapi_conformance/conformance.py
openapi_conformance/extension.py
openapi_conformance/strategies.py
openapi_conformance-0.1.0.dist-info/WHEEL
openapi_conformance-0.1.0.dist-info/METADATA
openapi_conformance-0.1.0.dist-info/RECORD
