Metadata-Version: 2.1
Name: openapi-conformance
Version: 0.1.0
Summary: 
Author: Daniel Bradburn
Author-email: daniel@crunchrapps.com
Requires-Python: >=3.6,<4.0
Classifier: Programming Language :: Python :: 3
Classifier: Programming Language :: Python :: 3.6
Classifier: Programming Language :: Python :: 3.7
Requires-Dist: hypothesis (>=4.7,<5.0)
Requires-Dist: openapi_core (>=0.8,<0.9)
Requires-Dist: toolz (>=0.9.0,<0.10.0)
Requires-Dist: validators (>=0.12.4,<0.13.0)
Requires-Dist: werkzeug (>=0.14.1,<0.15.0)
